pydiverse/__init__.py
pydiverse-0.0.1.dist-info/METADATA
pydiverse-0.0.1.dist-info/WHEEL
pydiverse-0.0.1.dist-info/top_level.txt
pydiverse-0.0.1.dist-info/RECORD
