Metadata-Version: 2.1
Name: pydiverse
Version: 0.0.1
Summary: A collection of nicely interoperable libraries for data pipeline orchestration allowing for both SQL target and in-memory operation.
Home-page: https://github.com/pydiverse/pydiverse
Author: QuantCo, Inc.
Author-email: noreply@quantco.com
Classifier: Programming Language :: Python :: 3
Classifier: Programming Language :: Python :: 3.8
Classifier: Programming Language :: Python :: 3.9
Classifier: Programming Language :: Python :: 3.10
Requires-Python: >=3.8
